ixmp4/__init__.py
ixmp4/__main__.py
ixmp4/cli/__init__.py
ixmp4/cli/platforms.py
ixmp4/cli/server.py
ixmp4/cli/utils.py
ixmp4/conf/__init__.py
ixmp4/conf/auth.py
ixmp4/conf/base.py
ixmp4/conf/credentials.py
ixmp4/conf/logging/debug.json
ixmp4/conf/logging/development.json
ixmp4/conf/logging/production.json
ixmp4/conf/logging/server.json
ixmp4/conf/manager.py
ixmp4/conf/settingsmodel.py
ixmp4/conf/toml.py
ixmp4/conf/user.py
ixmp4/core/__init__.py
ixmp4/core/base.py
ixmp4/core/checkpoints.py
ixmp4/core/decorators.py
ixmp4/core/exceptions.py
ixmp4/core/iamc/__init__.py
ixmp4/core/iamc/data.py
ixmp4/core/iamc/variable.py
ixmp4/core/meta.py
ixmp4/core/model.py
ixmp4/core/optimization/__init__.py
ixmp4/core/optimization/base.py
ixmp4/core/optimization/data.py
ixmp4/core/optimization/equation.py
ixmp4/core/optimization/indexset.py
ixmp4/core/optimization/parameter.py
ixmp4/core/optimization/scalar.py
ixmp4/core/optimization/table.py
ixmp4/core/optimization/variable.py
ixmp4/core/platform.py
ixmp4/core/region.py
ixmp4/core/run.py
ixmp4/core/scenario.py
ixmp4/core/unit.py
ixmp4/core/utils.py
ixmp4/data/__init__.py
ixmp4/data/abstract/__init__.py
ixmp4/data/abstract/annotations.py
ixmp4/data/abstract/base.py
ixmp4/data/abstract/checkpoint.py
ixmp4/data/abstract/docs.py
ixmp4/data/abstract/iamc/__init__.py
ixmp4/data/abstract/iamc/datapoint.py
ixmp4/data/abstract/iamc/measurand.py
ixmp4/data/abstract/iamc/timeseries.py
ixmp4/data/abstract/iamc/variable.py
ixmp4/data/abstract/meta.py
ixmp4/data/abstract/model.py
ixmp4/data/abstract/optimization/__init__.py
ixmp4/data/abstract/optimization/base.py
ixmp4/data/abstract/optimization/equation.py
ixmp4/data/abstract/optimization/indexset.py
ixmp4/data/abstract/optimization/parameter.py
ixmp4/data/abstract/optimization/scalar.py
ixmp4/data/abstract/optimization/table.py
ixmp4/data/abstract/optimization/variable.py
ixmp4/data/abstract/region.py
ixmp4/data/abstract/run.py
ixmp4/data/abstract/scenario.py
ixmp4/data/abstract/unit.py
ixmp4-0.13.1.dist-info/METADATA
ixmp4-0.13.1.dist-info/WHEEL
ixmp4-0.13.1.dist-info/entry_points.txt
ixmp4-0.13.1.dist-info/licenses/LICENSE
ixmp4-0.13.1.dist-info/RECORD
