Metadata-Version: 2.4
Name: ixmp4
Version: 0.13.1
Summary: a data warehouse for scenario analysis
License: MIT
License-File: LICENSE
Author: Max Wolschlager
Author-email: wolschlager@iiasa.ac.at
Requires-Python: >=3.10,<3.14
Classifier: License :: OSI Approved :: MIT License
Classifier: Programming Language :: Python :: 3
Classifier: Programming Language :: Python :: 3.10
Classifier: Programming Language :: Python :: 3.11
Classifier: Programming Language :: Python :: 3.12
Classifier: Programming Language :: Python :: 3.13
Requires-Dist: PyJWT (>=2.4.0)
Requires-Dist: SQLAlchemy-Utils (>=0.41.0)
Requires-Dist: SQLAlchemy[mypy] (>=2.0.22)
Requires-Dist: alembic (>=1.12.0)
Requires-Dist: fastapi (>=0.100.0)
Requires-Dist: httpx[http2] (>=0.25.0)
Requires-Dist: openpyxl (>=3.0.9)
Requires-Dist: pandas (>=2.1.1)
Requires-Dist: pandera (>=0.24.0)
Requires-Dist: psycopg[binary] (>=3.1.12)
Requires-Dist: pydantic (>=2.3.0)
Requires-Dist: pydantic-settings (>=2.1.0)
Requires-Dist: python-dotenv (>=1.0.1)
Requires-Dist: rich (>=13.5.2)
Requires-Dist: toml (>=0.10.2)
Requires-Dist: typer (>=0.9.0)
Project-URL: Documentation, https://docs.ece.iiasa.ac.at/projects/ixmp4
Project-URL: Homepage, https://software.ece.iiasa.ac.at
Project-URL: Repository, https://github.com/iiasa/ixmp4
